pylect/__init__.py
pylect/__main__.py
pylect/cli.py
pylect/constants.py
pylect/esv.py
pylect/holyday.py
pylect/lectionary.py
pylect/psalter.py
pylect/data/lectionary.json
pylect/data/psalter.json
pylect-0.3.3.dist-info/LICENSE.txt
pylect-0.3.3.dist-info/METADATA
pylect-0.3.3.dist-info/WHEEL
pylect-0.3.3.dist-info/entry_points.txt
pylect-0.3.3.dist-info/top_level.txt
pylect-0.3.3.dist-info/RECORD
