Metadata-Version: 2.1
Name: pylect
Version: 0.3.3
Summary: Tools for working with the Anglican lectionary.
Author-email: William Wingate <wtwingate@gmail.com>
License: MIT License
Project-URL: Repository, https://github.com/wtwingate/pylect
Keywords: lectionary,liturgy,calendar,anglican
Classifier: Development Status :: 4 - Beta
Classifier: License :: OSI Approved :: MIT License
Classifier: Operating System :: OS Independent
Classifier: Programming Language :: Python :: 3
Requires-Python: >=3.12
License-File: LICENSE.txt
Requires-Dist: pyperclip
Requires-Dist: python-dateutil
Requires-Dist: python-dotenv
Requires-Dist: requests
Provides-Extra: dev
Requires-Dist: black ; extra == 'dev'
Requires-Dist: isort ; extra == 'dev'
Requires-Dist: pylint ; extra == 'dev'
Requires-Dist: pytest ; extra == 'dev'
